fred_macroeco/__init__.py
fred_macroeco/server.py
fred_macroeco/data/__init__.py
fred_macroeco/data/fred_client.py
fred_macroeco/data/fred_map_series.py
macroeconomic_mcp_server-0.1.1.dist-info/METADATA
macroeconomic_mcp_server-0.1.1.dist-info/WHEEL
macroeconomic_mcp_server-0.1.1.dist-info/entry_points.txt
macroeconomic_mcp_server-0.1.1.dist-info/top_level.txt
macroeconomic_mcp_server-0.1.1.dist-info/RECORD
