Metadata-Version: 2.4
Name: macroeconomic-mcp-server
Version: 0.1.1
Summary: Add your description here
Requires-Python: >=3.13
Requires-Dist: colorama>=0.4.6
Requires-Dist: mcp[cli]>=1.6.0
Requires-Dist: numpy>=2.2.4
Requires-Dist: pandas>=2.2.3
Requires-Dist: python-dotenv>=1.1.0
Requires-Dist: requests>=2.32.3
